nonebot_plugin_farm/__init__.py
nonebot_plugin_farm/command.py
nonebot_plugin_farm/config/item.json
nonebot_plugin_farm/config/level.json
nonebot_plugin_farm/config/soil.json
nonebot_plugin_farm/config.py
nonebot_plugin_farm/database/database.py
nonebot_plugin_farm/database/plant.py
nonebot_plugin_farm/database/user.py
nonebot_plugin_farm/database/userItem.py
nonebot_plugin_farm/database/userPlant.py
nonebot_plugin_farm/database/userSeed.py
nonebot_plugin_farm/database/userSign.py
nonebot_plugin_farm/database/userSoil.py
nonebot_plugin_farm/database/userSteal.py
nonebot_plugin_farm/dbService.py
nonebot_plugin_farm/event/event.py
nonebot_plugin_farm/farm/farm.py
nonebot_plugin_farm/farm/shop.py
nonebot_plugin_farm/json.py
nonebot_plugin_farm/log/log.md
nonebot_plugin_farm/request.py
nonebot_plugin_farm/resource/1.png
nonebot_plugin_farm/resource/background/background.jpg
nonebot_plugin_farm/resource/background/background.png
nonebot_plugin_farm/resource/background/expansion.png
nonebot_plugin_farm/resource/background/frame.png
nonebot_plugin_farm/resource/background/ripe.png
nonebot_plugin_farm/resource/db/plant-test.db
nonebot_plugin_farm/resource/db/plant.db
nonebot_plugin_farm/resource/db/version.json
nonebot_plugin_farm/resource/plant/ATTomato/1.png
nonebot_plugin_farm/resource/plant/ATTomato/2.png
nonebot_plugin_farm/resource/plant/ATTomato/3.png
nonebot_plugin_farm/resource/plant/ATTomato/4.png
nonebot_plugin_farm/resource/plant/ATTomato/5.png
nonebot_plugin_farm/resource/plant/ATTomato/icon.png
nonebot_plugin_farm/resource/plant/basic/0.png
nonebot_plugin_farm/resource/plant/basic/9.png
nonebot_plugin_farm/resource/plant/一点红/1.png
nonebot_plugin_farm/resource/plant/一点红/2.png
nonebot_plugin_farm/resource/plant/一点红/3.png
nonebot_plugin_farm/resource/plant/一点红/4.png
nonebot_plugin_farm/resource/plant/一点红/5.png
nonebot_plugin_farm/resource/plant/一点红/icon.png
nonebot_plugin_farm/resource/plant/三七/1.png
nonebot_plugin_farm/resource/plant/三七/2.png
nonebot_plugin_farm-1.5.7.dist-info/LICENSE
nonebot_plugin_farm-1.5.7.dist-info/METADATA
nonebot_plugin_farm-1.5.7.dist-info/WHEEL
nonebot_plugin_farm-1.5.7.dist-info/RECORD
