Metadata-Version: 2.3
Name: nonebot_plugin_farm
Version: 1.5.7
Summary: 快乐的农场时光
License: GPL-3.0-or-later
Author: Art_Sakura
Author-email: 1754798088@qq.com
Requires-Python: >=3.9,<4.0
Classifier: License :: OSI Approved :: GNU General Public License v3 or later (GPLv3+)
Classifier: Programming Language :: Python :: 3
Classifier: Programming Language :: Python :: 3.9
Classifier: Programming Language :: Python :: 3.10
Classifier: Programming Language :: Python :: 3.11
Classifier: Programming Language :: Python :: 3.12
Classifier: Programming Language :: Python :: 3.13
Requires-Dist: aiosqlite (>=0.21.0,<0.22.0)
Requires-Dist: httpx (>=0.27.2,<1.0.0)
Requires-Dist: nonebot-plugin-alconna (>=0.46.3,<1.0.0)
Requires-Dist: nonebot-plugin-apscheduler (>=0.5.0,<0.6.0)
Requires-Dist: nonebot-plugin-localstore (>=0.7.4,<0.8.0)
Requires-Dist: nonebot-plugin-uninfo (>=0.6.0,<0.7.0)
Requires-Dist: nonebot-plugin-waiter (>=0.8.1,<0.9.0)
Requires-Dist: nonebot2 (>=2.1.3,<3.0.0)
Requires-Dist: pydantic (<=2.10.6)
Requires-Dist: rich (>=13.9.4,<14.0.0)
Requires-Dist: zhenxun-utils (>=0.2.1,<0.3.0)
Project-URL: Repository, https://github.com/Shu-Ying/nonebot_plugin_farm.git
